{
  "format_version": "1.13.0",
  "minecraft:entity": {
    "description": {
      "identifier": "cpoc:rampage_instant_explosion",
      "is_spawnable": false,
      "is_summonable": true,
      "is_experimental": false
    },
    "component_groups": {
      "cpoc:despawn": {
        "minecraft:instant_despawn": {}
      }
    },
    "components": {
      "minecraft:collision_box": {
        "width": 0.0,
        "height": 0.0
      },
      "minecraft:damage_sensor": {
        "triggers": [
          {
            "cause": "all",
            "deals_damage": false
          }
        ]
      },
      "minecraft:physics": {},
      "minecraft:pushable": {
        "is_pushable": false,
        "is_pushable_by_piston": true
      },
      "minecraft:explode": {
        "breaks_blocks": true,
        "causes_fire": true,
        "destroy_affected_by_griefing": true,
        "fuse_lit": true,
        "fuse_length": 0,
        "power": 5
      },
      "minecraft:conditional_bandwidth_optimization": {
        "default_values": {
          "max_optimized_distance": 80.0,
          "max_dropped_ticks": 7,
          "use_motion_prediction_hints": true
        }
      },
      "minecraft:timer": {
        "time": 0.25,
        "looping": true,
        "time_down_event": {
          "event": "cpoc:despawn",
          "target": "self"
        }
      }
    },
    "events": {
      "cpoc:despawn": {
        "add": {
          "component_groups": [
            "cpoc:despawn"
          ]
        }
      }
    }
  }
}